aclib/cv/__init__.py
aclib/cv/_typing.py
aclib/cv/__API__/color.py
aclib/cv/__API__/dotset.py
aclib/cv/__API__/dotsetlib.py
aclib/cv/__API__/dsetsimmat.py
aclib/cv/__API__/image.py
aclib/cv/__API__/target.py
aclib_cv-1.1.0.dist-info/licenses/LICENSE
aclib_cv-1.1.0.dist-info/METADATA
aclib_cv-1.1.0.dist-info/WHEEL
aclib_cv-1.1.0.dist-info/top_level.txt
aclib_cv-1.1.0.dist-info/RECORD
